atsim.potentials-0.4.0-py3.8-nspkg.pth
atsim/potentials/__init__.py
atsim/potentials/_common.py
atsim/potentials/_dlpoly_writeTABEAM.py
atsim/potentials/_dlpoly_writeTABLE.py
atsim/potentials/_eam_potential.py
atsim/potentials/_lammpsWriteEAM.py
atsim/potentials/_lammps_writeTABLE.py
atsim/potentials/_modifiers.py
atsim/potentials/_multi_range_potential_form.py
atsim/potentials/_potential.py
atsim/potentials/_tablereaders.py
atsim/potentials/_util.py
atsim/potentials/eam_tabulation.py
atsim/potentials/pair_tabulation.py
atsim/potentials/potentialforms.py
atsim/potentials/potentialfunctions.py
atsim/potentials/tableforms.py
atsim/potentials/config/__init__.py
atsim/potentials/config/_cexprtk_potential_function.py
atsim/potentials/config/_common.py
atsim/potentials/config/_config_parser.py
atsim/potentials/config/_configuration.py
atsim/potentials/config/_eam_potential_builder.py
atsim/potentials/config/_filtered_config_parser.py
atsim/potentials/config/_modifier_registry.py
atsim/potentials/config/_multi_range_parser.py
atsim/potentials/config/_pair_potential_builder.py
atsim/potentials/config/_potential_form.py
atsim/potentials/config/_potential_form_builder.py
atsim/potentials/config/_potential_form_registry.py
atsim/potentials/config/_pymath.py
atsim/potentials/config/_python_potential_function.py
atsim/potentials/config/_table_form_builder.py
atsim/potentials/config/_tabulation_factories.py
atsim/potentials/referencedata/__init__.py
atsim/potentials/referencedata/_data.py
atsim/potentials/referencedata/_reference_data.py
atsim/potentials/spline/__init__.py
atsim/potentials/tools/__init__.py
atsim/potentials/tools/potable/__init__.py
atsim/potentials/tools/potable/_actions.py
atsim/potentials/tools/potable/_query_actions.py
tests/config/__init__.py
tests/config/_common.py
tests/config/test_config_potential_form_builder.py
tests/config/test_config_potential_form_registry.py
tests/config/test_configparser.py
tests/config/test_configuration_eam.py
atsim.potentials-0.4.0.dist-info/LICENSE
atsim.potentials-0.4.0.dist-info/METADATA
atsim.potentials-0.4.0.dist-info/NOTICE
atsim.potentials-0.4.0.dist-info/WHEEL
atsim.potentials-0.4.0.dist-info/entry_points.txt
atsim.potentials-0.4.0.dist-info/namespace_packages.txt
atsim.potentials-0.4.0.dist-info/top_level.txt
atsim.potentials-0.4.0.dist-info/RECORD
