Metadata-Version: 2.1
Name: atsim.potentials
Version: 0.4.0
Summary: atsim.potentials provides tools for working with pair and embedded atom method potential models including tabulation routines for DL_POLY and LAMMPS
Home-page: https://github.com/mjdrushton/atsim-potentials
Author: M.J.D. Rushton
Author-email: m.j.d.rushton@gmail.com
License: Apache License (2.0)
Download-URL: https://github.com/mjdrushton/atsim-potentials/archive/master.zip
Keywords: pair potentials,embedded atom model,LAMMPS,DL_POLY,potential tabulation,atomistic,simulation,molecular dynamics,atomic scale
Platform: UNKNOWN
Classifier: License :: OSI Approved :: Apache Software License
Classifier: Programming Language :: Python :: 3
Classifier: Programming Language :: Python :: 3.6
Classifier: Programming Language :: Python :: 3.7
Classifier: Programming Language :: Python :: 3.8
Classifier: Programming Language :: Python :: 3.9
Classifier: Topic :: Scientific/Engineering
Requires-Dist: cexprtk (>=0.3.4)
Requires-Dist: pyparsing (>=2.2.0)
Requires-Dist: scipy
Requires-Dist: setuptools
Requires-Dist: wrapt (>=1.12.1)
Requires-Dist: funcsigs (==1.0.2) ; python_version < "3.5"
Requires-Dist: openpyxl (==2.6.4) ; python_version <= "3.5.*"
Requires-Dist: openpyxl (>=3.0.0) ; python_version >= "3.6"
